{
  "benchmarks": {
    "action_check_bulk": {
      "median_display": "4.68ms",
      "median_ns": "4676508",
      "min_display": "4.59ms",
      "min_ns": "4594378"
    },
    "action_check_individual": {
      "median_display": "4.41ms",
      "median_ns": "4410619",
      "min_display": "4.33ms",
      "min_ns": "4332949"
    },
    "transform_read_bulk_2d": {
      "median_display": "15.39ms",
      "median_ns": "15392699",
      "min_display": "15.13ms",
      "min_ns": "15133397"
    },
    "transform_read_bulk_3d": {
      "median_display": "13.67ms",
      "median_ns": "13669580",
      "min_display": "13.51ms",
      "min_ns": "13507809"
    },
    "transform_read_individual_2d": {
      "median_display": "12.14ms",
      "median_ns": "12135225",
      "min_display": "11.87ms",
      "min_ns": "11873472"
    },
    "transform_read_individual_3d": {
      "median_display": "9.39ms",
      "median_ns": "9391292",
      "min_display": "9.23ms",
      "min_ns": "9232346"
    },
    "transform_update_bulk_2d": {
      "median_display": "15.89ms",
      "median_ns": "15889872",
      "min_display": "15.49ms",
      "min_ns": "15488467"
    },
    "transform_update_bulk_3d": {
      "median_display": "13.45ms",
      "median_ns": "13448113",
      "min_display": "13.14ms",
      "min_ns": "13136891"
    },
    "transform_update_individual_2d": {
      "median_display": "12.41ms",
      "median_ns": "12405154",
      "min_display": "12.02ms",
      "min_ns": "12020715"
    },
    "transform_update_individual_3d": {
      "median_display": "12.12ms",
      "median_ns": "12118678",
      "min_display": "12.02ms",
      "min_ns": "12024579"
    }
  },
  "environment": {
    "godot_debug": true,
    "rust_debug": false
  },
  "timestamp": "2025-12-08T15:47:42.519923118+00:00"
}
